craved/__init__.py
craved/eda.py
craved/external_indices.py
craved/gap.py
craved/internal_indices.py
craved/supervised.py
craved-0.2a3.data/scripts/craved-warehouse
craved-0.2a3.dist-info/DESCRIPTION.rst
craved-0.2a3.dist-info/LICENSE.txt
craved-0.2a3.dist-info/METADATA
craved-0.2a3.dist-info/RECORD
craved-0.2a3.dist-info/WHEEL
craved-0.2a3.dist-info/metadata.json
craved-0.2a3.dist-info/top_level.txt
