Metadata-Version: 2.0
Name: craved
Version: 0.2a3
Summary: Buddi-CRAVeD
Home-page: https://github.com/elixir-code/craved
Author: R Mukesh,NitinShravan
Author-email: reghu.mukesh@gmail.com,ntnshrav@gmail.com
License: 3-clause BSD
Keywords: cluster analysis validation visualisation internal external indices
Platform: UNKNOWN
Classifier: Development Status :: 2 - Pre-Alpha
Classifier: License :: OSI Approved :: BSD License
Classifier: Programming Language :: Python :: 3 :: Only
Classifier: Topic :: Scientific/Engineering
Requires-Dist: matplotlib
Requires-Dist: seaborn
Requires-Dist: scipy
Requires-Dist: pandas
Requires-Dist: sklearn
Requires-Dist: h5py
Requires-Dist: hdbscan
Requires-Dist: numpy
